setup.py
info_asset/__init__.py
info_asset.egg-info/PKG-INFO
info_asset.egg-info/SOURCES.txt
info_asset.egg-info/dependency_links.txt
info_asset.egg-info/not-zip-safe
info_asset.egg-info/top_level.txt